{
    "security.workspace.trust.untrustedFiles": "open",
    "editor.cursorSmoothCaretAnimation": "on",
    "workbench.list.smoothScrolling": true,
    "editor.smoothScrolling": true,
    "gitlens.defaultDateFormat": null,
    "[css]": {
        "editor.defaultFormatter": "aeschli.vscode-css-formatter"
    },
    "editor.fontWeight": "500",
    "editor.fontLigatures": true,
    "editor.fontFamily": "lekton nerd font,Operator Mono Lig light,droid sans mono, blexmono nerd font light,roboto mono, cascadia code pl light, cascade mono, cascadia mono light, mono lisa, droid sans mono, victor mono, fira code, 'Courier New', monospace",
    "files.associations": {
        "*.ts": "typescript"
    },
    "editor.codeActionsOnSave": {},
    "editor.autoClosingBrackets": "always",
    "debug.javascript.autoAttachFilter": "disabled",
    "editor.renderWhitespace": "none",
    "[php]": {
        "editor.defaultFormatter": "bmewburn.vscode-intelephense-client"
    },
    "terminal.integrated.fontSize": 18,
    "redhat.telemetry.enabled": true,
    "typescript.preferences.importModuleSpecifier": "project-relative",
    "[jsonc]": {
        "editor.defaultFormatter": "vscode.json-language-features"
    },
    "[html]": {
        "editor.defaultFormatter": "vscode.html-language-features"
    },
    "[json]": {
        "editor.defaultFormatter": "vscode.json-language-features"
    },
    "angular.forceStrictTemplates": true,
    "[scss]": {
        "editor.defaultFormatter": "vscode.css-language-features"
    },
    "javascript.updateImportsOnFileMove.enabled": "always",
    "typescript.updateImportsOnFileMove.enabled": "always",
    "git.autofetch": true,
    "[typescriptreact]": {
        "editor.defaultFormatter": "vscode.typescript-language-features"
    },
    "terminal.integrated.defaultProfile.windows": "Git Bash",
    "terminal.integrated.scrollback": 5000,
    "terminal.integrated.smoothScrolling": true,
    "javascript.inlayHints.parameterNames.enabled": "all",
    "javascript.inlayHints.parameterNames.suppressWhenArgumentMatchesName": false,
    "typescript.inlayHints.parameterNames.enabled": "all",
    "typescript.inlayHints.parameterNames.suppressWhenArgumentMatchesName": false,
    "editor.fontSize": 20,
    "editor.lineHeight": 1.3,
    "gitlens.ai.model": "",
    "window.commandCenter": false,
    "diffEditor.codeLens": true,
    "gitlens.graph.onlyFollowFirstParent": true,
    "git.blame.statusBarItem.enabled": true,
    "workbench.editor.highlightModifiedTabs": true,
    "editor.letterSpacing": 0.5,
    "editor.minimap.renderCharacters": false,
    "gitlens.graph.dateStyle": "absolute",
    "gitlens.graph.dateFormat": "DD/MM/YYYY HH:mm",
    "workbench.colorTheme": "Aura Dracula Spirit (Soft)",
    "workbench.activityBar.location": "hidden",
    "workbench.editor.showTabs": "single",
    "workbench.statusBar.visible": false,
    "workbench.startupEditor": "none",
    "workbench.tips.enabled": false,
    "breadcrumbs.enabled": false,
    "workbench.sideBar.location": "right",
    "workbench.iconTheme": "material-icon-theme",
    "material-icon-theme.hidesExplorerArrows": true,
    "workbench.tree.enableStickyScroll": false,
    "workbench.tree.renderIndentGuides": "none",
    "workbench.tree.indent": 8,
    "explorer.compactFolders": false,
    "explorer.confirmDragAndDrop": false,
    "explorer.confirmDelete": false,
    "explorer.decorations.badges": false,
    "window.zoomLevel": -1,
    "custom-ui-style.electron": {
        "titleBarStyle": "hiddenInset",
        "trafficLightPosition": {
            "x": 20,
            "y": 16
        }
    },
    "custom-ui-style.stylesheet": {
        ".notification-toast": "box-shadow: none !important",
        ".quick-input-widget.show-file-icons": "box-shadow: none !important",
        ".quick-input-widget": "top: 25vh !important",
        ".quick-input-list .scrollbar": "display: none",
        ".monaco-action-bar.quick-input-inline-action-bar": "display: none",
        ".editor-widget.find-widget": "box-shadow: none; border-radius: 4px",
        ".quick-input-titlebar": "background: #100B15 !important",
        ".monaco-workbench .part.editor > .content .editor-group-container > .title.title-border-bottom:after": "display: none",
        ".monaco-scrollable-element > .shadow.top": "display: none",
        ".sidebar .title-label": "padding: 0 !important",
        ".sidebar": "border: none !important",
        ".monaco-workbench .monaco-list:not(.element-focused):focus:before": "outline: none !important",
        ".monaco-list-row.focused": "outline: none !important",
        ".monaco-editor .scroll-decoration": "display: none",
        ".title-actions": "display: none !important",
        ".title.show-file-icons .label-container .monaco-icon-label.file-icon": "justify-content: center; padding: 0 !important",
        ".title .monaco-icon-label:after": "margin-right: 0",
        ".monaco-workbench .part.editor > .content .editor-group-container > .title > .label-container > .title-label": "padding-left: 60px",
        ".title .monaco-icon-label.file-icon": "margin: 0 60px",
        ".monaco-editor .cursors-layer .cursor": "background-image: linear-gradient(135deg, #ffaffc 10%, #DA70D6 100%)",
        ".monaco-sash.horizontal:hover": "background-color: #DA70D6 !important",
        ".monaco-sash.horizontal": "background-color: #a277ff; height: 2px;",
        ".composite.title.has-composite-bar.has-actions": "border-top: 0px solid #a277ff !important",
        ".pane-header": "border-top: 0px solid #a277ff !important",
        ".action-label": "border-bottom-color: #a277ff !important",
    },
    "custom-ui-style.font.sansSerif": "Dank Mono",
    "editor.cursorBlinking": "solid",
    "editor.cursorStyle": "block",
    "workbench.colorCustomizations": {
        "editorCursor.background": "#000000",
        "editorOverviewRuler.wordHighlightStrongForeground": "#0000",
        "editorOverviewRuler.selectionHighlightForeground": "#0000",
        "editorOverviewRuler.rangeHighlightForeground": "#0000",
        "editorOverviewRuler.wordHighlightForeground": "#0000",
        "editorOverviewRuler.bracketMatchForeground": "#0000",
        "editorOverviewRuler.findMatchForeground": "#0000",
        "editorOverviewRuler.modifiedForeground": "#0000",
        "editorOverviewRuler.deletedForeground": "#0000",
        "editorOverviewRuler.warningForeground": "#0000",
        "editorOverviewRuler.addedForeground": "#0000",
        "editorOverviewRuler.errorForeground": "#0000",
        "editorOverviewRuler.infoForeground": "#0000",
        "editorOverviewRuler.border": "#0000",
        "[Aura Dracula Spirit (Soft)]": {
            "editorSuggestWidget.selectedBackground": "#3A334B",
            "sideBar.background": "#191521"
        },
        "panelTitle.activeBorder": "#a277ff",
        "contrastBorder": "#a277ff",
        "activityBar.activeBackground": "#1cd5db",
        "activityBar.background": "#1cd5db",
        "activityBar.foreground": "#15202b",
        "activityBar.inactiveForeground": "#15202b99",
        "activityBarBadge.background": "#e21ddc",
        "activityBarBadge.foreground": "#e7e7e7",
        "commandCenter.border": "#e7e7e799",
        "editorGroup.border": "#1cd5db",
        "panel.border": "#1cd5db",
        "sash.hoverBorder": "#1cd5db",
        "sideBar.border": "#1cd5db",
        "statusBar.background": "#16a9ae",
        "statusBar.border": "#16a9ae",
        "statusBar.debuggingBackground": "#ae1b16",
        "statusBar.debuggingBorder": "#ae1b16",
        "statusBar.debuggingForeground": "#e7e7e7",
        "statusBar.foreground": "#e7e7e7",
        "statusBarItem.hoverBackground": "#1cd5db",
        "statusBarItem.remoteBackground": "#16a9ae",
        "statusBarItem.remoteForeground": "#e7e7e7",
        "tab.activeBorder": "#1cd5db",
        "titleBar.activeBackground": "#16a9ae",
        "titleBar.activeForeground": "#e7e7e7",
        "titleBar.border": "#16a9ae",
        "titleBar.inactiveBackground": "#16a9ae99",
        "titleBar.inactiveForeground": "#e7e7e799",
        "editor.lineHighlightBackground": "#1073cf2d",
        "editor.lineHighlightBorder": "#9fced11f"
    },
    "editor.tokenColorCustomizations": {
        "textMateRules": [
            {
                "scope": "comment",
                "settings": {
                    "fontStyle": "italic"
                }
            }
        ]
    },
    "editor.stickyScroll.enabled": false,
    "editor.colorDecorators": false,
    "editor.codeLens": false,
    "editor.links": false,
    "editor.parameterHints.enabled": false,
    "editor.hover.enabled": "off",
    "files.trimTrailingWhitespace": true,
    "files.insertFinalNewline": true,
    "scm.diffDecorations": "all",
    "editor.lineNumbers": "relative",
    "editor.detectIndentation": true,
    "editor.showFoldingControls": "never",
    "editor.guides.indentation": false,
    "editor.scrollbar.horizontal": "hidden",
    "editor.scrollbar.vertical": "hidden",
    "editor.overviewRulerBorder": false,
    "editor.hideCursorInOverviewRuler": true,
    "editor.tabCompletion": "on",
    "editor.snippetSuggestions": "top",
    "emmet.triggerExpansionOnTab": true,
    "extensions.ignoreRecommendations": true,
    "workbench.editor.enablePreview": false,
    "window.menuBarVisibility": "toggle",
    "window.titleBarStyle": "native",
    "editor.minimap.showSlider": "always",
    "workbench.secondarySideBar.defaultVisibility": "hidden",
    "window.customTitleBarVisibility": "never",
    "workbench.preferredDarkColorTheme": "Aura Dracula Spirit (Soft)",
    "editor.guides.highlightActiveIndentation": "always",
    "editor.inlayHints.enabled": "off",
    "editor.wordWrap": "off",
    "diffEditor.wordWrap": "off",
    "editor.guides.bracketPairs": false,
    "blockman.n04ColorComboPreset": "Small Galaxy (Gradients)",
    "scm.diffDecorationsGutterPattern": {
        "added": true
    },
}
